django_auth_adfs/__init__.py
django_auth_adfs/backend.py
django_auth_adfs/config.py
django_auth_adfs/drf-urls.py
django_auth_adfs/drf_urls.py
django_auth_adfs/exceptions.py
django_auth_adfs/middleware.py
django_auth_adfs/rest_framework.py
django_auth_adfs/signals.py
django_auth_adfs/templates/django_auth_adfs/login_failed.html
django_auth_adfs/urls.py
django_auth_adfs/views.py
django_auth_adfs-1.16.0.dist-info/METADATA
django_auth_adfs-1.16.0.dist-info/WHEEL
django_auth_adfs-1.16.0.dist-info/licenses/LICENSE
django_auth_adfs-1.16.0.dist-info/RECORD
