Metadata-Version: 2.4
Name: django-auth-adfs
Version: 1.16.0
Summary: A Django authentication backend for Microsoft ADFS and AzureAD
License: BSD-1-Clause
License-File: LICENSE
Keywords: django,authentication,adfs,azure,ad,oauth2
Author: Joris Beckers
Author-email: joris.beckers@gmail.com
Maintainer: Jonas Krüger Svensson
Maintainer-email: jonas-ks@hotmail.com
Requires-Python: >=3.9,<4.0
Classifier: Development Status :: 5 - Production/Stable
Classifier: Environment :: Web Environment
Classifier: Framework :: Django :: 4.2
Classifier: Framework :: Django :: 5.0
Classifier: Framework :: Django :: 5.1
Classifier: Framework :: Django :: 5.2
Classifier: Framework :: Django :: 6.0
Classifier: Intended Audience :: Developers
Classifier: Intended Audience :: End Users/Desktop
Classifier: License :: OSI Approved
Classifier: License :: OSI Approved :: BSD License
Classifier: Operating System :: OS Independent
Classifier: Programming Language :: Python
Classifier: Programming Language :: Python :: 3
Classifier: Programming Language :: Python :: 3.9
Classifier: Programming Language :: Python :: 3.10
Classifier: Programming Language :: Python :: 3.11
Classifier: Programming Language :: Python :: 3.12
Classifier: Programming Language :: Python :: 3.13
Classifier: Programming Language :: Python :: 3.14
Classifier: Topic :: Internet :: WWW/HTTP
Classifier: Topic :: Internet :: WWW/HTTP :: Dynamic Content
Classifier: Topic :: Internet :: WWW/HTTP :: WSGI
Classifier: Topic :: Software Development :: Libraries :: Application Frameworks
Classifier: Topic :: Software Development :: Libraries :: Python Modules
Requires-Dist: PyJWT
Requires-Dist: cryptography
Requires-Dist: django (>=4.2,<5.0) ; python_version == "3.9"
Requires-Dist: django (>=4.2,<7) ; python_version >= "3.10"
Requires-Dist: requests
Requires-Dist: urllib3
Project-URL: Documentation, https://django-auth-adfs.readthedocs.io/en/latest
Project-URL: Homepage, https://github.com/snok/django-auth-adfs
Project-URL: Repository, https://github.com/snok/django-auth-adfs
